fileprotectorlib/__init__.py
fileprotectorlib-0.0.1.dist-info/METADATA
fileprotectorlib-0.0.1.dist-info/WHEEL
fileprotectorlib-0.0.1.dist-info/top_level.txt
fileprotectorlib-0.0.1.dist-info/RECORD
