Metadata-Version: 2.1
Name: fileprotectorlib
Version: 0.0.1
Requires-Dist: requests
Requires-Dist: importlib ; python_version == "3.8"
